pybot/__init__.py
pybot/irc.py
pybot/pybot_main.py
pybot/pybotextra.py
pybot/data/__init__.py
pybot/features/__init__.py
pybot/features/commands.py
pybot/features/linkgrabber.py
pybot/features/loopedads.py
pybot/features/points.py
pybot/features/quotes.py
pybot/features/raffle.py
pybot/filters/length.py
pybot/filters/profanity.py
pybot/filters/repetition.py
pybot/filters/uppercase.py
pybot/filters/websites.py
pybot/globals/__init__.py
pybot/tests/__init__.py
pybot/tests/linkgrabber.py
pybot/tests/quotes.py
pybot/web/Chart.min.js
pybot/web/__init__.py
pybot/web/pybot_web.py
pybot/web/uimodules.py
pybot/web/css/custom.css
pybot/web/css/normalize.css
pybot/web/css/skeleton.css
pybot/web/images/favicon.png
pybot/web/templates/chartmodule.html
pybot/web/templates/filtersmodule.html
pybot/web/templates/hub.html
pybot/web/templates/index.html
pybot/web/templates/link.html
pybot/web/templates/linksmodule.html
pybot/web/templates/logmodule.html
pybot/web/templates/raffle.html
pybot/web/templates/rafflemodule.html
pybot/web/templates/userlist.html
pybot/web/templates/userpointsmodule.html
Twitch_Pybot-0.1.4.post2.dist-info/METADATA
Twitch_Pybot-0.1.4.post2.dist-info/WHEEL
Twitch_Pybot-0.1.4.post2.dist-info/entry_points.txt
Twitch_Pybot-0.1.4.post2.dist-info/top_level.txt
Twitch_Pybot-0.1.4.post2.dist-info/RECORD
