Metadata-Version: 2.1
Name: Twitch-Pybot
Version: 0.1.4.post2
Summary: A twitch bot with a web interface
Home-page: http://github.com/isivisi/pybot
Author: John Iannandrea
Author-email: jiannandrea@gmail.com
License: GNU
Keywords: bot twitch web interface
Platform: UNKNOWN
Classifier: Programming Language :: Python :: 3.5
Classifier: Operating System :: OS Independent
Requires-Python: >=3.5, <3.10
Requires-Dist: tornado (==4.3)
Requires-Dist: requests
